dogma_rust-0.2.6.dist-info/METADATA
dogma_rust-0.2.6.dist-info/WHEEL
dogma_rust/__init__.py
dogma_rust/__init__.pyi
dogma_rust/py.typed
dogma_rust/dogma_rust.cpython-311-x86_64-linux-gnu.so
dogma_rust-0.2.6.dist-info/RECORD
