Metadata-Version: 2.3
Name: dogma_rust
Version: 0.2.6
Classifier: Programming Language :: Rust
Classifier: Programming Language :: Python :: Implementation :: CPython
Classifier: Programming Language :: Python :: Implementation :: PyPy
Requires-Python: >=3.8
Project-URL: homepage, https://github.com/marcelroed/dogma-data
Project-URL: repository, https://github.com/marcelroed/dogma-data
